equimo/__init__.py
equimo/io.py
equimo/utils.py
equimo/conversion/__init__.py
equimo/conversion/utils.py
equimo/experimental/__init__.py
equimo/experimental/text.py
equimo/layers/__init__.py
equimo/layers/activation.py
equimo/layers/attention.py
equimo/layers/convolution.py
equimo/layers/downsample.py
equimo/layers/dropout.py
equimo/layers/ffn.py
equimo/layers/generic.py
equimo/layers/mamba.py
equimo/layers/norm.py
equimo/layers/patch.py
equimo/layers/posemb.py
equimo/layers/sharing.py
equimo/layers/squeeze_excite.py
equimo/layers/wavelet.py
equimo/models/__init__.py
equimo/models/emamodel.py
equimo/models/fastervit.py
equimo/models/lowformer.py
equimo/models/mlla.py
equimo/models/partialformer.py
equimo/models/reduceformer.py
equimo/models/shvit.py
equimo/models/vit.py
equimo/models/vssd.py
equimo/ops/scan.py
equimo-0.4.7.dist-info/licenses/LICENSE.md
equimo-0.4.7.dist-info/METADATA
equimo-0.4.7.dist-info/WHEEL
equimo-0.4.7.dist-info/top_level.txt
equimo-0.4.7.dist-info/RECORD
