Metadata-Version: 2.4
Name: Equimo
Version: 0.4.7
Summary: Implementation of popular vision models in Jax
Classifier: Development Status :: 4 - Beta
Classifier: Intended Audience :: Developers
Classifier: Intended Audience :: Science/Research
Classifier: License :: OSI Approved :: MIT License
Classifier: Topic :: Scientific/Engineering :: Artificial Intelligence
Classifier: Programming Language :: Python :: 3.11
Classifier: Programming Language :: Python :: 3.12
Classifier: Programming Language :: Python :: 3.13
Classifier: Programming Language :: Python :: 3.14
Requires-Python: >=3.11
License-File: LICENSE.md
Requires-Dist: einops>=0.8.0
Requires-Dist: equinox>=0.11.5
Requires-Dist: jax>=0.4.25
Requires-Dist: jaxlib>=0.4.25
Requires-Dist: loguru>=0.7.3
Requires-Dist: lz4>=4.4.3
Requires-Dist: requests>=2.32.3
Requires-Dist: semver>=3.0.4
Provides-Extra: torch
Requires-Dist: torch>=2.6.0; extra == "torch"
Requires-Dist: timm>=1.0.15; extra == "torch"
Provides-Extra: text
Requires-Dist: tensorflow>=2.18.1; extra == "text"
Requires-Dist: tensorflow-text>=2.18.1; extra == "text"
Provides-Extra: extras
Requires-Dist: matplotlib>=3.10.1; extra == "extras"
Requires-Dist: pillow>=11.1.0; extra == "extras"
Requires-Dist: scikit-learn>=1.6.1; extra == "extras"
Dynamic: license-file
